fhir/__init__.py
fhir/resources/__init__.py
fhir/resources/account.py
fhir/resources/activitydefinition.py
fhir/resources/actordefinition.py
fhir/resources/address.py
fhir/resources/administrableproductdefinition.py
fhir/resources/adverseevent.py
fhir/resources/age.py
fhir/resources/allergyintolerance.py
fhir/resources/annotation.py
fhir/resources/appointment.py
fhir/resources/appointmentresponse.py
fhir/resources/artifactassessment.py
fhir/resources/attachment.py
fhir/resources/auditevent.py
fhir/resources/availability.py
fhir/resources/backboneelement.py
fhir/resources/backbonetype.py
fhir/resources/base.py
fhir/resources/basic.py
fhir/resources/binary.py
fhir/resources/biologicallyderivedproduct.py
fhir/resources/biologicallyderivedproductdispense.py
fhir/resources/bodystructure.py
fhir/resources/bundle.py
fhir/resources/canonicalresource.py
fhir/resources/capabilitystatement.py
fhir/resources/careplan.py
fhir/resources/careteam.py
fhir/resources/chargeitem.py
fhir/resources/chargeitemdefinition.py
fhir/resources/citation.py
fhir/resources/claim.py
fhir/resources/claimresponse.py
fhir/resources/clinicalimpression.py
fhir/resources/clinicalusedefinition.py
fhir/resources/codeableconcept.py
fhir/resources/codeablereference.py
fhir/resources/codesystem.py
fhir/resources/coding.py
fhir/resources/communication.py
fhir/resources/communicationrequest.py
fhir/resources/compartmentdefinition.py
fhir/resources/composition.py
fhir/resources/conceptmap.py
fhir/resources/condition.py
fhir/resources/conditiondefinition.py
fhir/resources/consent.py
fhir/resources/contactdetail.py
fhir/resources/contactpoint.py
fhir/resources/contract.py
fhir/resources/contributor.py
fhir/resources/count.py
fhir/resources/coverage.py
fhir/resources/coverageeligibilityrequest.py
fhir/resources/coverageeligibilityresponse.py
fhir/resources/datarequirement.py
fhir/resources/datatype.py
fhir/resources/detectedissue.py
fhir/resources/device.py
fhir/resources/deviceassociation.py
fhir.resources-8.0.0.dist-info/AUTHORS.rst
fhir.resources-8.0.0.dist-info/LICENSE
fhir.resources-8.0.0.dist-info/METADATA
fhir.resources-8.0.0.dist-info/WHEEL
fhir.resources-8.0.0.dist-info/top_level.txt
fhir.resources-8.0.0.dist-info/RECORD
