Metadata-Version: 2.1
Name: fhir.resources
Version: 8.0.0
Summary: FHIR Resources as Model Class
Home-page: https://github.com/nazrulworld/fhir.resources
Author: Md Nazrul Islam
Author-email: email2nazrul@gmail.com
License: BSD license
Project-URL: CI: Travis, https://travis-ci.org/github/nazrulworld/fhir.resources
Project-URL: Coverage: codecov, https://codecov.io/gh/nazrulworld/fhir.resources
Project-URL: GitHub: issues, https://github.com/nazrulworld/fhir.resources/issues
Project-URL: GitHub: repo, https://github.com/nazrulworld/fhir.resources
Keywords: fhir,resources,python,hl7,health IT,healthcare
Classifier: Development Status :: 5 - Production/Stable
Classifier: Intended Audience :: Developers
Classifier: License :: OSI Approved :: BSD License
Classifier: Natural Language :: English
Classifier: Programming Language :: Python :: 3
Classifier: Programming Language :: Python :: 3 :: Only
Classifier: Programming Language :: Python :: 3.8
Classifier: Programming Language :: Python :: 3.9
Classifier: Programming Language :: Python :: 3.10
Classifier: Programming Language :: Python :: 3.11
Classifier: Programming Language :: Python :: 3.12
Classifier: Programming Language :: Python :: 3.13
Classifier: Programming Language :: Python :: 3.14
Classifier: Intended Audience :: Developers
Classifier: Intended Audience :: Education
Classifier: Intended Audience :: Healthcare Industry
Classifier: Intended Audience :: Information Technology
Classifier: Intended Audience :: Science/Research
Classifier: Operating System :: OS Independent
Classifier: Typing :: Typed
Requires-Python: >=3.8
Provides-Extra: yaml
Provides-Extra: xml
Provides-Extra: test
Provides-Extra: dev
Provides-Extra: all
License-File: LICENSE
License-File: AUTHORS.rst
